{
    "version": "1.5.23",
    "architecture": {
        "32bit": {
            "url": "https://github.com/suz-stripe/stripe-cli/releases/download/v1.5.23/stripe_1.5.23_windows_i386.zip",
            "bin": [
                "stripe.exe"
            ],
            "hash": "2d594ddce757dae24b977979ee9932550f38ead061014a99901e30164fb619bd"
        },
        "64bit": {
            "url": "https://github.com/suz-stripe/stripe-cli/releases/download/v1.5.23/stripe_1.5.23_windows_x86_64.zip",
            "bin": [
                "stripe.exe"
            ],
            "hash": "0d2b703aba4fa13e80baf906d08c10b3c6fe109dded9f519ed96b9925ed0be73"
        }
    },
    "homepage": "https://stripe.com",
    "license": "Apache 2.0",
    "description": "Stripe CLI utility"
}